sb_json_tools-0.10.2.dist-info/METADATA
sb_json_tools-0.10.2.dist-info/WHEEL
sb_json_tools-0.10.2.dist-info/entry_points.txt
sb_json_tools-0.10.2.dist-info/licenses/LICENSE
sb_json_tools/__init__.py
sb_json_tools/cli.py
sb_json_tools/exceptions.py
sb_json_tools/jsondiff.py
sb_json_tools/jt_val/__init__.py
sb_json_tools/jt_val/exceptions.py
sb_json_tools/py.typed
sb_json_tools/utils.py
sb_json_tools-0.10.2.dist-info/RECORD
