Metadata-Version: 2.1
Name: sb-json-tools
Version: 0.10.2
Summary: Tools for working with JSON files.
Author-Email: =?utf-8?q?Spr=C3=A5kbanken_at_the_University_of_Gothenburg?= <sb-info@svenska.gu.se>
License: MIT
Classifier: Development Status :: 4 - Beta
Classifier: Intended Audience :: Developers
Classifier: License :: OSI Approved :: MIT License
Classifier: Operating System :: Unix
Classifier: Operating System :: POSIX
Classifier: Programming Language :: Python :: 3.9
Classifier: Programming Language :: Python :: 3.10
Classifier: Programming Language :: Python :: 3.11
Classifier: Programming Language :: Python :: 3.12
Classifier: Programming Language :: Python :: Implementation :: CPython
Classifier: Topic :: Utilities
Project-URL: Bug tracker, https://github.com/spraakbanken/python-json-tools/issues
Project-URL: Repository, https://github.com/spraakbanken/python-json-tools
Project-URL: Homepage, https://github.com/spraakbanken/python-json-tools
Requires-Python: >=3.9
Requires-Dist: fastjsonschema>=2.19.1
Requires-Dist: typer>=0.12.3
Requires-Dist: json-arrays>=0.14.1
Requires-Dist: bump-my-version>=0.21.1; extra == "release"
Provides-Extra: release
